Workbook
Name Slicer_Location: #N/A
Name Slicer_Product_type: #N/A
Name Slicer_Supplier_name: #N/A
Name Slicer_Transportation_modes: #N/A

Sheet supply_chain_data
A1: Product type | B1: SKU | C1: Price | D1: Availability | E1: Number of products sold | F1: Revenue generated | G1: Customer demographics | H1: Stock levels | I1: Lead times | J1: Order quantities | K1: Shipping times | L1: Shipping carriers | M1: Shipping costs | N1: Supplier name | O1: Location | P1: Lead time | Q1: Production volumes | R1: Manufacturing lead time | S1: Manufacturing costs | T1: Inspection results | U1: Defect rates | V1: Transportation modes | W1: Routes | X1: Costs | Y1: Profit | Z1: Profit Margin
A2: haircare | B2: SKU0 | C2: 69.808006 | D2: 55 | E2: 802 | F2: 8661.9968 | G2: Non-binary | H2: 58 | I2: 7 | J2: 96 | K2: 4 | L2: Carrier B | M2: 2.9565721 | N2: Supplier 3 | O2: Mumbai | P2: 29 | Q2: 215 | R2: 29 | S2: 46.279879 | T2: Pending | U2: 0.22641036 | V2: Road | W2: Route B | X2: 187.75208 | Y2: =Table1[[#This Row],[Revenue generated]]-Table1[[#This Row],[Manufacturing costs]]-Table1[[#This Row],[Shipping costs]] -> 8612.7603 | Z2: =(Y2/F2) -> 0.99431581
A3: skincare | B3: SKU1 | C3: 14.843523 | D3: 95 | E3: 736 | F3: 7460.9001 | G3: Female | H3: 53 | I3: 30 | J3: 37 | K3: 2 | L3: Carrier A | M3: 9.7165748 | N3: Supplier 3 | O3: Mumbai | P3: 23 | Q3: 517 | R3: 30 | S3: 33.616769 | T3: Pending | U3: 4.854068 | V3: Road | W3: Route B | X3: 503.06558 | Y3: =Table1[[#This Row],[Revenue generated]]-Table1[[#This Row],[Manufacturing costs]]-Table1[[#This Row],[Shipping costs]] -> 7417.5667 | Z3: =(Y3/F3) -> 0.99419194
A4: haircare | B4: SKU2 | C4: 11.319683 | D4: 34 | E4: 8 | F4: 9577.7496 | G4: Unknown | H4: 1 | I4: 10 | J4: 88 | K4: 2 | L4: Carrier B | M4: 8.0544793 | N4: Supplier 1 | O4: Mumbai | P4: 12 | Q4: 971 | R4: 27 | S4: 30.688019 | T4: Pending | U4: 4.5805926 | V4: Air | W4: Route C | X4: 141.92028 | Y4: =Table1[[#This Row],[Revenue generated]]-Table1[[#This Row],[Manufacturing costs]]-Table1[[#This Row],[Shipping costs]] -> 9539.0071 | Z4: =(Y4/F4) -> 0.99595495
A5: skincare | B5: SKU3 | C5: 61.163343 | D5: 68 | E5: 83 | F5: 7766.8364 | G5: Non-binary | H5: 23 | I5: 13 | J5: 59 | K5: 6 | L5: Carrier C | M5: 1.7295686 | N5: Supplier 5 | O5: Kolkata | P5: 24 | Q5: 937 | R5: 18 | S5: 35.624741 | T5: Fail | U5: 4.7466486 | V5: Rail | W5: Route A | X5: 254.77616 | Y5: =Table1[[#This Row],[Revenue generated]]-Table1[[#This Row],[Manufacturing costs]]-Table1[[#This Row],[Shipping costs]] -> 7729.4821 | Z5: =(Y5/F5) -> 0.99519054
A6: skincare | B6: SKU4 | C6: 4.805496 | D6: 26 | E6: 871 | F6: 2686.5052 | G6: Non-binary | H6: 5 | I6: 3 | J6: 56 | K6: 8 | L6: Carrier A | M6: 3.8905479 | N6: Supplier 1 | O6: Delhi | P6: 5 | Q6: 414 | R6: 3 | S6: 92.065161 | T6: Fail | U6: 3.1455795 | V6: Air | W6: Route A | X6: 923.44063 | Y6: =Table1[[#This Row],[Revenue generated]]-Table1[[#This Row],[Manufacturing costs]]-Table1[[#This Row],[Shipping costs]] -> 2590.5494 | Z6: =(Y6/F6) -> 0.96428233
A7: haircare | B7: SKU5 | C7: 1.699976 | D7: 87 | E7: 147 | F7: 2828.3487 | G7: Non-binary | H7: 90 | I7: 27 | J7: 66 | K7: 3 | L7: Carrier B | M7: 4.4440989 | N7: Supplier 4 | O7: Bangalore | P7: 10 | Q7: 104 | R7: 17 | S7: 56.766476 | T7: Fail | U7: 2.7791935 | V7: Road | W7: Route A | X7: 235.46124 | Y7: =Table1[[#This Row],[Revenue generated]]-Table1[[#This Row],[Manufacturing costs]]-Table1[[#This Row],[Shipping costs]] -> 2767.1382 | Z7: =(Y7/F7) -> 0.97835819
A8: skincare | B8: SKU6 | C8: 4.0783329 | D8: 48 | E8: 65 | F8: 7823.4766 | G8: Male | H8: 11 | I8: 15 | J8: 58 | K8: 8 | L8: Carrier C | M8: 3.8807633 | N8: Supplier 3 | O8: Kolkata | P8: 14 | Q8: 314 | R8: 24 | S8: 1.0850686 | T8: Pending | U8: 1.0009106 | V8: Sea | W8: Route A | X8: 134.3691 | Y8: =Table1[[#This Row],[Revenue generated]]-Table1[[#This Row],[Manufacturing costs]]-Table1[[#This Row],[Shipping costs]] -> 7818.5107 | Z8: =(Y8/F8) -> 0.99936527
A9: cosmetics | B9: SKU7 | C9: 42.958384 | D9: 59 | E9: 426 | F9: 8496.1038 | G9: Female | H9: 93 | I9: 17 | J9: 11 | K9: 1 | L9: Carrier B | M9: 2.3483388 | N9: Supplier 4 | O9: Bangalore | P9: 22 | Q9: 564 | R9: 1 | S9: 99.466109 | T9: Fail | U9: 0.39817719 | V9: Road | W9: Route C | X9: 802.05631 | Y9: =Table1[[#This Row],[Revenue generated]]-Table1[[#This Row],[Manufacturing costs]]-Table1[[#This Row],[Shipping costs]] -> 8394.2894 | Z9: =(Y9/F9) -> 0.98801634
A10: cosmetics | B10: SKU8 | C10: 68.717597 | D10: 78 | E10: 150 | F10: 7517.3632 | G10: Female | H10: 5 | I10: 10 | J10: 15 | K10: 7 | L10: Carrier C | M10: 3.4047339 | N10: Supplier 4 | O10: Mumbai | P10: 13 | Q10: 769 | R10: 8 | S10: 11.423027 | T10: Pending | U10: 2.7098627 | V10: Sea | W10: Route B | X10: 505.55713 | Y10: =Table1[[#This Row],[Revenue generated]]-Table1[[#This Row],[Manufacturing costs]]-Table1[[#This Row],[Shipping costs]] -> 7502.5354 | Z10: =(Y10/F10) -> 0.99802753
A11: skincare | B11: SKU9 | C11: 64.015733 | D11: 35 | E11: 980 | F11: 4971.146 | G11: Unknown | H11: 14 | I11: 27 | J11: 83 | K11: 1 | L11: Carrier A | M11: 7.1666453 | N11: Supplier 2 | O11: Chennai | P11: 29 | Q11: 963 | R11: 23 | S11: 47.957602 | T11: Pending | U11: 3.8446145 | V11: Rail | W11: Route B | X11: 995.92946 | Y11: =Table1[[#This Row],[Revenue generated]]-Table1[[#This Row],[Manufacturing costs]]-Table1[[#This Row],[Shipping costs]] -> 4916.0217 | Z11: =(Y11/F11) -> 0.98891116
A12: skincare | B12: SKU10 | C12: 15.707796 | D12: 11 | E12: 996 | F12: 2330.9658 | G12: Non-binary | H12: 51 | I12: 13 | J12: 80 | K12: 2 | L12: Carrier C | M12: 8.6732112 | N12: Supplier 5 | O12: Kolkata | P12: 18 | Q12: 830 | R12: 5 | S12: 96.527353 | T12: Pass | U12: 1.7273139 | V12: Road | W12: Route B | X12: 806.10318 | Y12: =Table1[[#This Row],[Revenue generated]]-Table1[[#This Row],[Manufacturing costs]]-Table1[[#This Row],[Shipping costs]] -> 2225.7652 | Z12: =(Y12/F12) -> 0.95486825
A13: skincare | B13: SKU11 | C13: 90.63546 | D13: 95 | E13: 960 | F13: 6099.9441 | G13: Female | H13: 46 | I13: 23 | J13: 60 | K13: 1 | L13: Carrier A | M13: 4.5239431 | N13: Supplier 2 | O13: Kolkata | P13: 28 | Q13: 362 | R13: 11 | S13: 27.592363 | T13: Pending | U13: 0.021169821 | V13: Air | W13: Route A | X13: 126.72303 | Y13: =Table1[[#This Row],[Revenue generated]]-Table1[[#This Row],[Manufacturing costs]]-Table1[[#This Row],[Shipping costs]] -> 6067.8278 | Z13: =(Y13/F13) -> 0.99473498
... A101: haircare | B101: SKU99 | C101: 68.517833 | D101: 17 | E101: 627 | F101: 9185.1858 | G101: Unknown | H101: 55 | I101: 8 | J101: 59 | K101: 6 | L101: Carrier B | M101: 1.3110238 | N101: Supplier 2 | O101: Chennai | P101: 29 | Q101: 921 | R101: 2 | S101: 38.072899 | T101: Fail | U101: 0.34602729 | V101: Rail | W101: Route B | X101: 210.74301 | Y101: =Table1[[#This Row],[Revenue generated]]-Table1[[#This Row],[Manufacturing costs]]-Table1[[#This Row],[Shipping costs]] -> 9145.8019 | Z101: =(Y101/F101) -> 0.99571223

Sheet Sheet3
A3: Row Labels | B3: Sum of Revenue generated
A4: cosmetics | B4: 161521.27
A5: haircare | B5: 174455.39
A6: skincare | B6: 241628.16
A7: Grand Total | B7: 577604.82
A16: Row Labels | B16: Average of Shipping costs
A17: Air | B17: 6.0178394
A18: Rail | B18: 5.4690979
A19: Road | B19: 5.5421154
A20: Sea | B20: 4.9702938
A21: Grand Total | B21: 5.5481491
A32: Row Labels | B32: Sum of Revenue generated
A33: Chennai | B33: 119142.82
A34: Bangalore | B34: 102601.72
A35: Delhi | B35: 81027.701
A36: Kolkata | B36: 137077.55
A37: Mumbai | B37: 137755.03
A38: Grand Total | B38: 577604.82
B46: Row Labels | C46: Count of Inspection results
B47: Fail | C47: 100
B48: Pass | C48: 100
B49: Pending | C49: 100
B50: Grand Total | C50: 100

Sheet Sheet5
A3: Row Labels | B3: Average of Defect rates
A4: Supplier 1 | B4: 1.8036297
A5: Supplier 2 | B5: 2.3627501
A6: Supplier 3 | B6: 2.465786
A7: Supplier 4 | B7: 2.3373974
A8: Supplier 5 | B8: 2.6654083
A9: Grand Total | B9: 2.277158
A17: Sum of Revenue generated | B17: Sum of Lead times | D17: Sum of Shipping costs | E17: Sum of Profit | F17: Sum of Defect rates | G17: Sum of Number of products sold
A18: 577604.82 | B18: 1596 | D18: 554.81491 | E18: 572323.33 | F18: 227.7158 | G18: 46099

Sheet DASHBOARD
A1: Supply Chain Performance Dashboard
D2: Revenue | F2: Total Profit | H2: Shipping Cost | J2: Defects Rate | L2: Product Sold | N2: Lead Time
D4: =GETPIVOTDATA("[Measures].[Sum of Revenue generated]",Sheet5!$A$17) -> 577604.82 | F4: =GETPIVOTDATA("[Measures].[Sum of Profit]",Sheet5!$D$17) -> 572323.33 | H4: =GETPIVOTDATA("[Measures].[Sum of Shipping costs]",Sheet5!$D$17) -> 554.81491 | J4: =GETPIVOTDATA("[Measures].[Sum of Defect rates]",Sheet5!$D$17) -> 227.7158 | L4: =GETPIVOTDATA("[Measures].[Sum of Number of products sold]",Sheet5!$D$17) -> 46099 | N4: =GETPIVOTDATA("[Measures].[Sum of Lead times]",Sheet5!$B$17) -> 1596
